{
	"name": "Archrock_Delimited_UCM_ZIP_files",
	"properties": {
		"linkedServiceName": {
			"referenceName": "AzureBlobStorage1",
			"type": "LinkedServiceReference"
		},
		"parameters": {
			"container_name": {
				"type": "String"
			},
			"file_path": {
				"type": "String"
			},
			"file_name": {
				"type": "String"
			}
		},
		"annotations": [],
		"type": "DelimitedText",
		"typeProperties": {
			"location": {
				"type": "AzureBlobStorageLocation",
				"fileName": {
					"value": "@dataset().file_name",
					"type": "Expression"
				},
				"folderPath": {
					"value": "@dataset().file_path",
					"type": "Expression"
				},
				"container": {
					"value": "@dataset().container_name",
					"type": "Expression"
				}
			},
			"columnDelimiter": ",",
			"compressionCodec": "ZipDeflate",
			"escapeChar": "\"",
			"firstRowAsHeader": true,
			"quoteChar": "\""
		},
		"schema": []
	}
}